{
  "id": "act-121-1971",
  "type": "statute",
  "title": "Zákon Slovenskej národnej rady o ľudovej kontrole v Slovenskej socialistickej republice",
  "title_en": "Zákon Slovenskej národnej rady o ľudovej kontrole v Slovenskej socialistickej republice",
  "short_name": "121/1971 Z. z.",
  "status": "unknown",
  "url": "https://www.slov-lex.sk/ezbierky/pravne-predpisy/SK/ZZ/1971/121/",
  "description": "Official legal act listed in Slov-Lex: Zákon Slovenskej národnej rady o ľudovej kontrole v Slovenskej socialistickej republice",
  "provisions": [],
  "definitions": []
}