{
  "id": "act-128-1976",
  "type": "statute",
  "title": "Vyhláška Federálneho ministerstva dopravy o ciachovaní lodí vnútrozemskej plavby",
  "title_en": "Vyhláška Federálneho ministerstva dopravy o ciachovaní lodí vnútrozemskej plavby",
  "short_name": "128/1976 Z. z.",
  "status": "unknown",
  "url": "https://www.slov-lex.sk/ezbierky/pravne-predpisy/SK/ZZ/1976/128/",
  "description": "Official legal act listed in Slov-Lex: Vyhláška Federálneho ministerstva dopravy o ciachovaní lodí vnútrozemskej plavby",
  "provisions": [],
  "definitions": []
}