{
  "id": "act-107-1988",
  "type": "statute",
  "title": "Zákon Slovenskej národnej rady, ktorým sa mení a dopĺňa zákon o národných výboroch",
  "title_en": "Zákon Slovenskej národnej rady, ktorým sa mení a dopĺňa zákon o národných výboroch",
  "short_name": "107/1988 Z. z.",
  "status": "unknown",
  "url": "https://www.slov-lex.sk/ezbierky/pravne-predpisy/SK/ZZ/1988/107/",
  "description": "Official legal act listed in Slov-Lex: Zákon Slovenskej národnej rady, ktorým sa mení a dopĺňa zákon o národných výboroch",
  "provisions": [],
  "definitions": []
}