{
  "id": "act-446-2002",
  "type": "statute",
  "title": "Zákon o vzájomnej pomoci pri vymáhaní niektorých finančných pohľadávok",
  "title_en": "Zákon o vzájomnej pomoci pri vymáhaní niektorých finančných pohľadávok",
  "short_name": "446/2002 Z. z.",
  "status": "unknown",
  "url": "https://www.slov-lex.sk/ezbierky/pravne-predpisy/SK/ZZ/2002/446/",
  "description": "Official legal act listed in Slov-Lex: Zákon o vzájomnej pomoci pri vymáhaní niektorých finančných pohľadávok",
  "provisions": [],
  "definitions": []
}