{
  "id": "act-64-1997",
  "type": "statute",
  "title": "Zákon o užívaní pozemkov v zriadených záhradkových osadách a vyporiadaní vlastníctva k nim",
  "title_en": "Zákon o užívaní pozemkov v zriadených záhradkových osadách a vyporiadaní vlastníctva k nim",
  "short_name": "64/1997 Z. z.",
  "status": "unknown",
  "url": "https://www.slov-lex.sk/ezbierky/pravne-predpisy/SK/ZZ/1997/64/",
  "description": "Official legal act listed in Slov-Lex: Zákon o užívaní pozemkov v zriadených záhradkových osadách a vyporiadaní vlastníctva k nim",
  "provisions": [],
  "definitions": []
}