{
  "id": "act-61-1992",
  "type": "statute",
  "title": "Zákon České národní rady o Nejvyšším kontrolním úřadě České republiky",
  "title_en": "Zákon České národní rady o Nejvyšším kontrolním úřadě České republiky",
  "short_name": "61/1992 Z. z.",
  "status": "unknown",
  "url": "https://www.slov-lex.sk/ezbierky/pravne-predpisy/SK/ZZ/1992/61/",
  "description": "Official legal act listed in Slov-Lex: Zákon České národní rady o Nejvyšším kontrolním úřadě České republiky",
  "provisions": [],
  "definitions": []
}