{
  "id": "act-145-1948",
  "type": "statute",
  "title": "Vyhláška o úplném znění zákona o revisi první pozemkové reformy.",
  "title_en": "Vyhláška o úplném znění zákona o revisi první pozemkové reformy.",
  "short_name": "145/1948 Z. z.",
  "status": "unknown",
  "url": "https://www.slov-lex.sk/ezbierky/pravne-predpisy/SK/ZZ/1948/145/",
  "description": "Official legal act listed in Slov-Lex: Vyhláška o úplném znění zákona o revisi první pozemkové reformy.",
  "provisions": [],
  "definitions": []
}