{
  "id": "act-531-2023",
  "type": "statute",
  "title": "Vyhláška Ministerstva zdravotníctva Slovenskej republiky o kategorizácii ústavnej zdravotnej starostlivosti",
  "title_en": "Vyhláška Ministerstva zdravotníctva Slovenskej republiky o kategorizácii ústavnej zdravotnej starostlivosti",
  "short_name": "531/2023 Z. z.",
  "status": "unknown",
  "url": "https://www.slov-lex.sk/ezbierky/pravne-predpisy/SK/ZZ/2023/531/",
  "description": "Official legal act listed in Slov-Lex: Vyhláška Ministerstva zdravotníctva Slovenskej republiky o kategorizácii ústavnej zdravotnej starostlivosti",
  "provisions": [],
  "definitions": []
}