{
  "id": "act-125-1996",
  "type": "statute",
  "title": "Zákon Národnej rady Slovenskej republiky o nemorálnosti a protiprávnosti komunistického systému",
  "title_en": "Zákon Národnej rady Slovenskej republiky o nemorálnosti a protiprávnosti komunistického systému",
  "short_name": "125/1996 Z. z.",
  "status": "unknown",
  "url": "https://www.slov-lex.sk/ezbierky/pravne-predpisy/SK/ZZ/1996/125/",
  "description": "Official legal act listed in Slov-Lex: Zákon Národnej rady Slovenskej republiky o nemorálnosti a protiprávnosti komunistického systému",
  "provisions": [],
  "definitions": []
}