{
  "id": "act-137-1946",
  "type": "statute",
  "title": "Zákon o národních kulturních komisích pro správu státního kulturního majetku.",
  "title_en": "Zákon o národních kulturních komisích pro správu státního kulturního majetku.",
  "short_name": "137/1946 Z. z.",
  "status": "unknown",
  "url": "https://www.slov-lex.sk/ezbierky/pravne-predpisy/SK/ZZ/1946/137/",
  "description": "Official legal act listed in Slov-Lex: Zákon o národních kulturních komisích pro správu státního kulturního majetku.",
  "provisions": [],
  "definitions": []
}