{
  "id": "act-28-2002",
  "type": "statute",
  "title": "Vyhláška Národného bezpečnostného úradu o priemyselnej bezpečnosti",
  "title_en": "Vyhláška Národného bezpečnostného úradu o priemyselnej bezpečnosti",
  "short_name": "28/2002 Z. z.",
  "status": "unknown",
  "url": "https://www.slov-lex.sk/ezbierky/pravne-predpisy/SK/ZZ/2002/28/",
  "description": "Official legal act listed in Slov-Lex: Vyhláška Národného bezpečnostného úradu o priemyselnej bezpečnosti",
  "provisions": [],
  "definitions": []
}