{
  "id": "act-70-1994",
  "type": "statute",
  "title": "Ústavný zákon Národnej rady Slovenskej republiky o skrátení volebného obdobia Národnej rady Slovenskej republiky",
  "title_en": "Ústavný zákon Národnej rady Slovenskej republiky o skrátení volebného obdobia Národnej rady Slovenskej republiky",
  "short_name": "70/1994 Z. z.",
  "status": "unknown",
  "url": "https://www.slov-lex.sk/ezbierky/pravne-predpisy/SK/ZZ/1994/70/",
  "description": "Official legal act listed in Slov-Lex: Ústavný zákon Národnej rady Slovenskej republiky o skrátení volebného obdobia Národnej rady Slovenskej republiky",
  "provisions": [],
  "definitions": []
}