{
  "id": "act-59-1974",
  "type": "statute",
  "title": "Vyhláška Federálneho ministerstva dopravy o vykonávaní cestnej taxislužby",
  "title_en": "Vyhláška Federálneho ministerstva dopravy o vykonávaní cestnej taxislužby",
  "short_name": "59/1974 Z. z.",
  "status": "unknown",
  "url": "https://www.slov-lex.sk/ezbierky/pravne-predpisy/SK/ZZ/1974/59/",
  "description": "Official legal act listed in Slov-Lex: Vyhláška Federálneho ministerstva dopravy o vykonávaní cestnej taxislužby",
  "provisions": [],
  "definitions": []
}