{
  "id": "act-105-1980",
  "type": "statute",
  "title": "Vyhláška Ministerstva školstva Slovenskej socialistickej republiky o štúdiu na vysokých školách (študijné predpisy)",
  "title_en": "Vyhláška Ministerstva školstva Slovenskej socialistickej republiky o štúdiu na vysokých školách (študijné predpisy)",
  "short_name": "105/1980 Z. z.",
  "status": "unknown",
  "url": "https://www.slov-lex.sk/ezbierky/pravne-predpisy/SK/ZZ/1980/105/",
  "description": "Official legal act listed in Slov-Lex: Vyhláška Ministerstva školstva Slovenskej socialistickej republiky o štúdiu na vysokých školách (študijné predpisy)",
  "provisions": [],
  "definitions": []
}