{
  "id": "act-593-1992",
  "type": "statute",
  "title": "Zákon České národní rady o rezervách pro zjištění základu daně z příjmů",
  "title_en": "Zákon České národní rady o rezervách pro zjištění základu daně z příjmů",
  "short_name": "593/1992 Z. z.",
  "status": "unknown",
  "url": "https://www.slov-lex.sk/ezbierky/pravne-predpisy/SK/ZZ/1992/593/",
  "description": "Official legal act listed in Slov-Lex: Zákon České národní rady o rezervách pro zjištění základu daně z příjmů",
  "provisions": [],
  "definitions": []
}