{
  "id": "act-19-1956",
  "type": "statute",
  "title": "Nariadenie o zrušení niektorých ministerstiev a ústredných orgánov štátnej správy",
  "title_en": "Nariadenie o zrušení niektorých ministerstiev a ústredných orgánov štátnej správy",
  "short_name": "19/1956 Z. z.",
  "status": "unknown",
  "url": "https://www.slov-lex.sk/ezbierky/pravne-predpisy/SK/ZZ/1956/19/",
  "description": "Official legal act listed in Slov-Lex: Nariadenie o zrušení niektorých ministerstiev a ústredných orgánov štátnej správy",
  "provisions": [],
  "definitions": []
}