{
  "id": "act-123-1999",
  "type": "statute",
  "title": "Vyhláška Národnej banky Slovenska o vydaní bankoviek po 5 000 Sk vzoru 1999 do obehu",
  "title_en": "Vyhláška Národnej banky Slovenska o vydaní bankoviek po 5 000 Sk vzoru 1999 do obehu",
  "short_name": "123/1999 Z. z.",
  "status": "unknown",
  "url": "https://www.slov-lex.sk/ezbierky/pravne-predpisy/SK/ZZ/1999/123/",
  "description": "Official legal act listed in Slov-Lex: Vyhláška Národnej banky Slovenska o vydaní bankoviek po 5 000 Sk vzoru 1999 do obehu",
  "provisions": [],
  "definitions": []
}