{
  "id": "act-23-1993",
  "type": "statute",
  "title": "Uznesenie vlády Slovenskej republiky o udelení amnestie vo veciach priestupkov",
  "title_en": "Uznesenie vlády Slovenskej republiky o udelení amnestie vo veciach priestupkov",
  "short_name": "23/1993 Z. z.",
  "status": "unknown",
  "url": "https://www.slov-lex.sk/ezbierky/pravne-predpisy/SK/ZZ/1993/23/",
  "description": "Official legal act listed in Slov-Lex: Uznesenie vlády Slovenskej republiky o udelení amnestie vo veciach priestupkov",
  "provisions": [],
  "definitions": []
}