{
  "id": "act-85-2001",
  "type": "statute",
  "title": "Úplné znenie zákona Národnej rady Slovenskej republiky č. 274/1994 Z. z. o Sociálnej poisťovni",
  "title_en": "Úplné znenie zákona Národnej rady Slovenskej republiky č. 274/1994 Z. z. o Sociálnej poisťovni",
  "short_name": "85/2001 Z. z.",
  "status": "unknown",
  "url": "https://www.slov-lex.sk/ezbierky/pravne-predpisy/SK/ZZ/2001/85/",
  "description": "Official legal act listed in Slov-Lex: Úplné znenie zákona Národnej rady Slovenskej republiky č. 274/1994 Z. z. o Sociálnej poisťovni",
  "provisions": [],
  "definitions": []
}