{
  "id": "act-447-2004",
  "type": "statute",
  "title": "Nariadenie vlády Slovenskej republiky o zvýšení stupnice platových taríf príslušníkov Hasičského a záchranného zboru",
  "title_en": "Nariadenie vlády Slovenskej republiky o zvýšení stupnice platových taríf príslušníkov Hasičského a záchranného zboru",
  "short_name": "447/2004 Z. z.",
  "status": "unknown",
  "url": "https://www.slov-lex.sk/ezbierky/pravne-predpisy/SK/ZZ/2004/447/",
  "description": "Official legal act listed in Slov-Lex: Nariadenie vlády Slovenskej republiky o zvýšení stupnice platových taríf príslušníkov Hasičského a záchranného zboru",
  "provisions": [],
  "definitions": []
}