{
  "id": "act-92-1950",
  "type": "statute",
  "title": "Vyhláška ministerstiev zdravotníctva a spravodlivosti o zániku činnosti štátnych veterinárnych vyšetrovacích ústavov",
  "title_en": "Vyhláška ministerstiev zdravotníctva a spravodlivosti o zániku činnosti štátnych veterinárnych vyšetrovacích ústavov",
  "short_name": "92/1950 Z. z.",
  "status": "unknown",
  "url": "https://www.slov-lex.sk/ezbierky/pravne-predpisy/SK/ZZ/1950/92/",
  "description": "Official legal act listed in Slov-Lex: Vyhláška ministerstiev zdravotníctva a spravodlivosti o zániku činnosti štátnych veterinárnych vyšetrovacích ústavov",
  "provisions": [],
  "definitions": []
}