{
  "id": "act-36-1978",
  "type": "statute",
  "title": "Zákon Slovenskej národnej rady o divadelnej činnosti (divadelný zákon)",
  "title_en": "Zákon Slovenskej národnej rady o divadelnej činnosti (divadelný zákon)",
  "short_name": "36/1978 Z. z.",
  "status": "unknown",
  "url": "https://www.slov-lex.sk/ezbierky/pravne-predpisy/SK/ZZ/1978/36/",
  "description": "Official legal act listed in Slov-Lex: Zákon Slovenskej národnej rady o divadelnej činnosti (divadelný zákon)",
  "provisions": [],
  "definitions": []
}