{
  "id": "act-60-1966",
  "type": "statute",
  "title": "Vládna vyhláška o výnimočnom poskytovaní dôchodku niektorým pracujúcim dôchodcom",
  "title_en": "Vládna vyhláška o výnimočnom poskytovaní dôchodku niektorým pracujúcim dôchodcom",
  "short_name": "60/1966 Z. z.",
  "status": "unknown",
  "url": "https://www.slov-lex.sk/ezbierky/pravne-predpisy/SK/ZZ/1966/60/",
  "description": "Official legal act listed in Slov-Lex: Vládna vyhláška o výnimočnom poskytovaní dôchodku niektorým pracujúcim dôchodcom",
  "provisions": [],
  "definitions": []
}