{
  "id": "act-49-1954",
  "type": "statute",
  "title": "Nariadenie, ktorým sa mení názov Slovenskej univerzity v Bratislave.",
  "title_en": "Nariadenie, ktorým sa mení názov Slovenskej univerzity v Bratislave.",
  "short_name": "49/1954 Z. z.",
  "status": "unknown",
  "url": "https://www.slov-lex.sk/ezbierky/pravne-predpisy/SK/ZZ/1954/49/",
  "description": "Official legal act listed in Slov-Lex: Nariadenie, ktorým sa mení názov Slovenskej univerzity v Bratislave.",
  "provisions": [],
  "definitions": []
}