{
  "id": "act-277-2012",
  "type": "statute",
  "title": "Vyhláška Úradu pre reguláciu sieťových odvetví, ktorou sa ustanovujú štandardy kvality dodávky tepla",
  "title_en": "Vyhláška Úradu pre reguláciu sieťových odvetví, ktorou sa ustanovujú štandardy kvality dodávky tepla",
  "short_name": "277/2012 Z. z.",
  "status": "unknown",
  "url": "https://www.slov-lex.sk/ezbierky/pravne-predpisy/SK/ZZ/2012/277/",
  "description": "Official legal act listed in Slov-Lex: Vyhláška Úradu pre reguláciu sieťových odvetví, ktorou sa ustanovujú štandardy kvality dodávky tepla",
  "provisions": [],
  "definitions": []
}