{
  "id": "act-42-1947",
  "type": "statute",
  "title": "Zákon o některých opatřeních ve stavebnictví souvisících s dvouletým hospodářským plánem.",
  "title_en": "Zákon o některých opatřeních ve stavebnictví souvisících s dvouletým hospodářským plánem.",
  "short_name": "42/1947 Z. z.",
  "status": "unknown",
  "url": "https://www.slov-lex.sk/ezbierky/pravne-predpisy/SK/ZZ/1947/42/",
  "description": "Official legal act listed in Slov-Lex: Zákon o některých opatřeních ve stavebnictví souvisících s dvouletým hospodářským plánem.",
  "provisions": [],
  "definitions": []
}