{
  "id": "act-121-1978",
  "type": "statute",
  "title": "Branný zákon (úplné znenie branného zákona, ako vyplýva z neskorších zákonných zmien a doplnkov)",
  "title_en": "Branný zákon (úplné znenie branného zákona, ako vyplýva z neskorších zákonných zmien a doplnkov)",
  "short_name": "121/1978 Z. z.",
  "status": "unknown",
  "url": "https://www.slov-lex.sk/ezbierky/pravne-predpisy/SK/ZZ/1978/121/",
  "description": "Official legal act listed in Slov-Lex: Branný zákon (úplné znenie branného zákona, ako vyplýva z neskorších zákonných zmien a doplnkov)",
  "provisions": [],
  "definitions": []
}