{
  "id": "act-145-1968",
  "type": "statute",
  "title": "Vyhláška Ministerstva financií a Ústrednej rady odborov o fonde kultúrnych a sociálnych potrieb a o pobádacom fonde",
  "title_en": "Vyhláška Ministerstva financií a Ústrednej rady odborov o fonde kultúrnych a sociálnych potrieb a o pobádacom fonde",
  "short_name": "145/1968 Z. z.",
  "status": "unknown",
  "url": "https://www.slov-lex.sk/ezbierky/pravne-predpisy/SK/ZZ/1968/145/",
  "description": "Official legal act listed in Slov-Lex: Vyhláška Ministerstva financií a Ústrednej rady odborov o fonde kultúrnych a sociálnych potrieb a o pobádacom fonde",
  "provisions": [],
  "definitions": []
}