{
  "id": "act-152-1989",
  "type": "statute",
  "title": "Nariadenie vlády Slovenskej socialistickej republiky o oblastnom plánovaní v Slovenskej socialistickej republike",
  "title_en": "Nariadenie vlády Slovenskej socialistickej republiky o oblastnom plánovaní v Slovenskej socialistickej republike",
  "short_name": "152/1989 Z. z.",
  "status": "unknown",
  "url": "https://www.slov-lex.sk/ezbierky/pravne-predpisy/SK/ZZ/1989/152/",
  "description": "Official legal act listed in Slov-Lex: Nariadenie vlády Slovenskej socialistickej republiky o oblastnom plánovaní v Slovenskej socialistickej republike",
  "provisions": [],
  "definitions": []
}