{
  "id": "act-101-1949",
  "type": "statute",
  "title": "Vyhláška ministra dopravy o prenesení koncesie pre drobnú železnicu Vítkovice-Zábřeh",
  "title_en": "Vyhláška ministra dopravy o prenesení koncesie pre drobnú železnicu Vítkovice-Zábřeh",
  "short_name": "101/1949 Z. z.",
  "status": "unknown",
  "url": "https://www.slov-lex.sk/ezbierky/pravne-predpisy/SK/ZZ/1949/101/",
  "description": "Official legal act listed in Slov-Lex: Vyhláška ministra dopravy o prenesení koncesie pre drobnú železnicu Vítkovice-Zábřeh",
  "provisions": [],
  "definitions": []
}