{
  "id": "act-7-1961",
  "type": "statute",
  "title": "Vyhláška ministra zahraničných vecí o Obchodnej zmluve medzi Československou socialistickou republikou a Japonskom",
  "title_en": "Vyhláška ministra zahraničných vecí o Obchodnej zmluve medzi Československou socialistickou republikou a Japonskom",
  "short_name": "7/1961 Z. z.",
  "status": "unknown",
  "url": "https://www.slov-lex.sk/ezbierky/pravne-predpisy/SK/ZZ/1961/7/",
  "description": "Official legal act listed in Slov-Lex: Vyhláška ministra zahraničných vecí o Obchodnej zmluve medzi Československou socialistickou republikou a Japonskom",
  "provisions": [],
  "definitions": []
}