{
  "id": "act-388-1992",
  "type": "statute",
  "title": "Vyhláška Federálneho ministerstva obrany o zriadení pobočky vyššieho vojenského súdu v Olomouci",
  "title_en": "Vyhláška Federálneho ministerstva obrany o zriadení pobočky vyššieho vojenského súdu v Olomouci",
  "short_name": "388/1992 Z. z.",
  "status": "unknown",
  "url": "https://www.slov-lex.sk/ezbierky/pravne-predpisy/SK/ZZ/1992/388/",
  "description": "Official legal act listed in Slov-Lex: Vyhláška Federálneho ministerstva obrany o zriadení pobočky vyššieho vojenského súdu v Olomouci",
  "provisions": [],
  "definitions": []
}