{
  "id": "act-25-1961",
  "type": "statute",
  "title": "Zákonné opatrenie Predsedníctva Národného zhromaždenia, ktorým sa mení zákon č. 41/1953 Zb.",
  "title_en": "Zákonné opatrenie Predsedníctva Národného zhromaždenia, ktorým sa mení zákon č. 41/1953 Zb.",
  "short_name": "25/1961 Z. z.",
  "status": "unknown",
  "url": "https://www.slov-lex.sk/ezbierky/pravne-predpisy/SK/ZZ/1961/25/",
  "description": "Official legal act listed in Slov-Lex: Zákonné opatrenie Predsedníctva Národného zhromaždenia, ktorým sa mení zákon č. 41/1953 Zb.",
  "provisions": [],
  "definitions": []
}