{
  "id": "act-48-1960",
  "type": "statute",
  "title": "Vyhláška ministra financií o stiahnutí štátoviek po 1 Kčs vzoru 1953",
  "title_en": "Vyhláška ministra financií o stiahnutí štátoviek po 1 Kčs vzoru 1953",
  "short_name": "48/1960 Z. z.",
  "status": "unknown",
  "url": "https://www.slov-lex.sk/ezbierky/pravne-predpisy/SK/ZZ/1960/48/",
  "description": "Official legal act listed in Slov-Lex: Vyhláška ministra financií o stiahnutí štátoviek po 1 Kčs vzoru 1953",
  "provisions": [],
  "definitions": []
}