{
  "id": "act-199-1994",
  "type": "statute",
  "title": "Zákon Národnej rady Slovenskej republiky o psychologickej činnosti a Slovenskej komore psychológov",
  "title_en": "Zákon Národnej rady Slovenskej republiky o psychologickej činnosti a Slovenskej komore psychológov",
  "short_name": "199/1994 Z. z.",
  "status": "unknown",
  "url": "https://www.slov-lex.sk/ezbierky/pravne-predpisy/SK/ZZ/1994/199/",
  "description": "Official legal act listed in Slov-Lex: Zákon Národnej rady Slovenskej republiky o psychologickej činnosti a Slovenskej komore psychológov",
  "provisions": [],
  "definitions": []
}