{
  "id": "act-152-1992",
  "type": "statute",
  "title": "Nařízení vlády České republiky o ochranných pásmech přírodních léčivých zdrojů lázeňského místa Františkovy Lázně",
  "title_en": "Nařízení vlády České republiky o ochranných pásmech přírodních léčivých zdrojů lázeňského místa Františkovy Lázně",
  "short_name": "152/1992 Z. z.",
  "status": "unknown",
  "url": "https://www.slov-lex.sk/ezbierky/pravne-predpisy/SK/ZZ/1992/152/",
  "description": "Official legal act listed in Slov-Lex: Nařízení vlády České republiky o ochranných pásmech přírodních léčivých zdrojů lázeňského místa Františkovy Lázně",
  "provisions": [],
  "definitions": []
}