{
  "id": "act-314-2018",
  "type": "statute",
  "title": "Zákon o Ústavnom súde Slovenskej republiky a o zmene a doplnení niektorých zákonov",
  "title_en": "Zákon o Ústavnom súde Slovenskej republiky a o zmene a doplnení niektorých zákonov",
  "short_name": "314/2018 Z. z.",
  "status": "unknown",
  "url": "https://www.slov-lex.sk/ezbierky/pravne-predpisy/SK/ZZ/2018/314/",
  "description": "Official legal act listed in Slov-Lex: Zákon o Ústavnom súde Slovenskej republiky a o zmene a doplnení niektorých zákonov",
  "provisions": [],
  "definitions": []
}